fractal_model_api/__init__.py
fractal_model_api/client.py
fractal_model_api/const.py
fractal_model_api/json_utils.py
fractal_model_api/logger_config.py
fractal_model_api/reader.py
fractal_model_api/service/__init__.py
fractal_model_api/service/base.py
fractal_model_api/service/optimizer/__init__.py
fractal_model_api/service/optimizer/base.py
fractal_model_api/service/optimizer/get_optimized_schedule_lt.py
fractal_model_api-0.2.0.dist-info/METADATA
fractal_model_api-0.2.0.dist-info/WHEEL
fractal_model_api-0.2.0.dist-info/RECORD
